karrio/mappers/shipengine/__init__.py
karrio/mappers/shipengine/mapper.py
karrio/mappers/shipengine/proxy.py
karrio/mappers/shipengine/settings.py
karrio/plugins/shipengine/__init__.py
karrio/providers/shipengine/__init__.py
karrio/providers/shipengine/address.py
karrio/providers/shipengine/error.py
karrio/providers/shipengine/rate.py
karrio/providers/shipengine/tracking.py
karrio/providers/shipengine/units.py
karrio/providers/shipengine/utils.py
karrio/providers/shipengine/shipment/__init__.py
karrio/providers/shipengine/shipment/cancel.py
karrio/providers/shipengine/shipment/create.py
karrio/schemas/shipengine/__init__.py
karrio/schemas/shipengine/address_validation_request.py
karrio/schemas/shipengine/address_validation_response.py
karrio/schemas/shipengine/error_response.py
karrio/schemas/shipengine/rate_request.py
karrio/schemas/shipengine/rate_response.py
karrio/schemas/shipengine/shipment_cancel_request.py
karrio/schemas/shipengine/shipment_cancel_response.py
karrio/schemas/shipengine/shipment_request.py
karrio/schemas/shipengine/shipment_response.py
karrio/schemas/shipengine/tracking_request.py
karrio/schemas/shipengine/tracking_response.py
karrio_shipengine-2026.1.4.dist-info/METADATA
karrio_shipengine-2026.1.4.dist-info/WHEEL
karrio_shipengine-2026.1.4.dist-info/entry_points.txt
karrio_shipengine-2026.1.4.dist-info/top_level.txt
karrio_shipengine-2026.1.4.dist-info/RECORD
